scyllaft-1.6.3.dist-info/METADATA
scyllaft-1.6.3.dist-info/WHEEL
scyllaft-1.6.3.dist-info/license_files/LICENSE
scyllaft/_internal/__init__.pyi
scyllaft/_internal/load_balancing.pyi
scyllaft/_internal/extra_types.pyi
scyllaft/_internal/exceptions.pyi
scyllaft/_internal/query_builder.pyi
scyllaft/py.typed
scyllaft/load_balancing.py
scyllaft/exceptions.py
scyllaft/__init__.py
scyllaft/query_builder.py
scyllaft/extra_types.py
scyllaft/_internal.abi3.so
scyllaft-1.6.3.dist-info/RECORD
