Metadata-Version: 2.3
Name: scyllaft
Version: 1.6.3
Classifier: Typing :: Typed
Classifier: Topic :: Database
Classifier: Development Status :: 4 - Beta
Classifier: Programming Language :: Rust
Classifier: Operating System :: MacOS
Classifier: Operating System :: Microsoft
Classifier: Operating System :: POSIX :: Linux
Classifier: Intended Audience :: Developers
Classifier: Topic :: Database :: Front-Ends
License-File: LICENSE
Summary: Async scylla driver for python - FentechFork
Keywords: scylla,cassandra,async-driver,scylla-driver
Requires-Python: >=3.8, <4
